lxpy/__init__.py
lxpy/cipher.py
lxpy/encoding.py
lxpy/js.py
lxpy/lxdate.py
lxpy/lxheader.py
lxpy/lxml_check.py
lxpy/lxtools.py
lxpy/tracks.py
lxpy/encrypt/aes.py
lxpy/encrypt/des.py
lxpy/encrypt/hmac.py
lxpy/encrypt/md5.py
lxpy/encrypt/rc4.py
lxpy/encrypt/rsa.py
lxpy/encrypt/serpent.py
lxpy-1.3.9.dist-info/LICENSE.txt
lxpy-1.3.9.dist-info/METADATA
lxpy-1.3.9.dist-info/WHEEL
lxpy-1.3.9.dist-info/top_level.txt
lxpy-1.3.9.dist-info/RECORD
