Metadata-Version: 2.1
Name: lxpy
Version: 1.3.9
Summary: Web crawler and data processing toolkit !
Home-page: https://github.com/lixi5338619/lxpy.git
Author: ying5338619
Author-email: 125066648@qq.com
License: UNKNOWN
Platform: all
Requires-Dist: wheel
